{
   "criteria": {
       "has_sherd": {
           "trigger": "inventory_changed",
           "conditions": {
               "items": [
                   {
                       "items": "archer_pottery_sherd"
                   }
               ]
           }
       },
       "has_recipe": {
           "trigger": "recipe_unlocked",
           "conditions": {
               "recipe": "chalc:sherd/archer"
           }
       }
   },
   "requirements": [
       [
           "has_recipe",
           "has_sherd"
       ]
   ],
   "rewards": {
       "recipes": [
           "chalc:sherd/archer"
       ]
   }
}